{
  "year": 1973,
  "gp": "allemagne",
  "grid": [
    {
      "position": 1,
      "driver": "J.STEWART",
      "constructor": null,
      "engine": null
    },
    {
      "position": 2,
      "driver": "R.PETERSON",
      "constructor": null,
      "engine": null
    },
    {
      "position": 3,
      "driver": "F.CEVERT",
      "constructor": null,
      "engine": null
    },
    {
      "position": 4,
      "driver": "J.ICKX",
      "constructor": "McLaren",
      "engine": null
    },
    {
      "position": 5,
      "driver": "N.LAUDA",
      "constructor": null,
      "engine": null
    },
    {
      "position": 6,
      "driver": "C.REUTEMANN",
      "constructor": null,
      "engine": null
    },
    {
      "position": 7,
      "driver": "P.REVSON",
      "constructor": "McLaren",
      "engine": null
    },
    {
      "position": 8,
      "driver": "D.HULME",
      "constructor": "McLaren",
      "engine": null
    },
    {
      "position": 9,
      "driver": "J.BELTOISE",
      "constructor": null,
      "engine": null
    },
    {
      "position": 10,
      "driver": "C.REGAZZONI",
      "constructor": null,
      "engine": null
    },
    {
      "position": 11,
      "driver": "C.PACE",
      "constructor": null,
      "engine": null
    },
    {
      "position": 12,
      "driver": "H.PESCAROLO",
      "constructor": null,
      "engine": null
    },
    {
      "position": 13,
      "driver": "W.FITTIPALDI",
      "constructor": null,
      "engine": null
    },
    {
      "position": 14,
      "driver": "E.FITTIPALDI",
      "constructor": null,
      "engine": null
    },
    {
      "position": 15,
      "driver": "J.MASS",
      "constructor": null,
      "engine": null
    },
    {
      "position": 16,
      "driver": "R.STOMMELEN",
      "constructor": null,
      "engine": null
    },
    {
      "position": 17,
      "driver": "J.OLIVER",
      "constructor": null,
      "engine": null
    },
    {
      "position": 18,
      "driver": "M.HAILWOOD",
      "constructor": null,
      "engine": null
    },
    {
      "position": 19,
      "driver": "M.BEUTTLER",
      "constructor": null,
      "engine": null
    },
    {
      "position": 20,
      "driver": "G.HILL",
      "constructor": null,
      "engine": null
    },
    {
      "position": 21,
      "driver": "G.FOLLMER",
      "constructor": null,
      "engine": null
    },
    {
      "position": 22,
      "driver": "D.PURLEY",
      "constructor": null,
      "engine": null
    }
  ]
}