{
  "year": 1995,
  "gp": "japon",
  "grid": [
    {
      "position": 1,
      "driver": "M.SCHUMACHER",
      "constructor": null,
      "engine": "Renault"
    },
    {
      "position": 2,
      "driver": "J.ALESI",
      "constructor": "Ferrari",
      "engine": null
    },
    {
      "position": 3,
      "driver": "M.HAKKINEN",
      "constructor": "McLaren",
      "engine": "Mercedes"
    },
    {
      "position": 4,
      "driver": "D.HILL",
      "constructor": "Williams",
      "engine": "Renault"
    },
    {
      "position": 5,
      "driver": "G.BERGER",
      "constructor": "Ferrari",
      "engine": null
    },
    {
      "position": 6,
      "driver": "D.COULTHARD",
      "constructor": "Williams",
      "engine": "Renault"
    },
    {
      "position": 7,
      "driver": "E.IRVINE",
      "constructor": null,
      "engine": null
    },
    {
      "position": 8,
      "driver": "H.FRENTZEN",
      "constructor": null,
      "engine": null
    },
    {
      "position": 9,
      "driver": "J.HERBERT",
      "constructor": null,
      "engine": "Renault"
    },
    {
      "position": 10,
      "driver": "R.BARRICHELLO",
      "constructor": null,
      "engine": null
    },
    {
      "position": 11,
      "driver": "O.PANIS",
      "constructor": null,
      "engine": null
    },
    {
      "position": 12,
      "driver": "M.SALO",
      "constructor": null,
      "engine": null
    },
    {
      "position": 13,
      "driver": "U.KATAYAMA",
      "constructor": null,
      "engine": null
    },
    {
      "position": 14,
      "driver": "G.MORBIDELLI",
      "constructor": null,
      "engine": null
    },
    {
      "position": 15,
      "driver": "K.WENDLINGER",
      "constructor": null,
      "engine": null
    },
    {
      "position": 16,
      "driver": "P.LAMY",
      "constructor": null,
      "engine": null
    },
    {
      "position": 17,
      "driver": "L.BADOER",
      "constructor": null,
      "engine": null
    },
    {
      "position": 18,
      "driver": "T.INOUE",
      "constructor": null,
      "engine": null
    },
    {
      "position": 19,
      "driver": "A.MONTERMINI",
      "constructor": null,
      "engine": null
    },
    {
      "position": 20,
      "driver": "P.DINIZ",
      "constructor": null,
      "engine": null
    },
    {
      "position": 21,
      "driver": "R.MORENO",
      "constructor": null,
      "engine": null
    },
    {
      "position": 22,
      "driver": "B.GACHOT",
      "constructor": null,
      "engine": null
    },
    {
      "position": 23,
      "driver": "M.BLUNDELL",
      "constructor": "McLaren",
      "engine": "Mercedes"
    }
  ]
}