[
  {
    "lien_fiche": "https://www.autoscout24.fr/offres/opel-meriva-1-6-enjoy-essence-gris-ed0bc114-7fb7-4053-a2b0-04c57cb3a6c4",
    "prix": "€ 350",
    "marque": "Opel Meriva1.6 Enjoy",
    "localisation": "7471 GG GOOR",
    "kilometrage": 178228,
    "annee": 2003,
    "carburant": "Essence",
    "boite_de_vitesse": "Manuelle",
    "transmission": "Avant",
    "puissance": "64 kW (87 CH)",
    "type_de_vehicule": "Monospace",
    "sieges": 5,
    "portes": 5
  },
  {
    "lien_fiche": "https://www.autoscout24.fr/offres/volkswagen-touareg-5-0-v10-tdi-tiptronic-313cv-diesel-noir-690799a5-91f6-49de-9176-d5ad7e4f1e22",
    "prix": "€ 3 500",
    "marque": "Volkswagen Touareg5.0 V10 tdi tiptronic 313cv",
    "localisation": "20062 Cassano d'Adda - Milano -  MI",
    "kilometrage": 275000,
    "annee": 2003,
    "carburant": "Diesel",
    "boite_de_vitesse": "Automatique",
    "transmission": "Arrière",
    "puissance": "230 kW (313 CH)",
    "type_de_vehicule": "SUV/4x4/Pick-Up",
    "sieges": 5,
    "portes": 5
  },
  {
    "lien_fiche": "https://www.autoscout24.fr/offres/opel-corsa-d-150-jahre-opel-mit-lpg-gpl-blanc-f2cb02e6-7631-4a43-a54b-e2d245e86bbf",
    "prix": "€ 2 450",
    "marque": "Opel CorsaD 150 Jahre Opel mit LPG",
    "localisation": "41363 Juechen",
    "kilometrage": 152877,
    "annee": 2012,
    "carburant": "Électrique",
    "boite_de_vitesse": "Manuelle",
    "transmission": "Avant",
    "puissance": "63 kW (86 CH)",
    "type_de_vehicule": "Citadine",
    "sieges": 5,
    "portes": 2
  },
  {
    "lien_fiche": "https://www.autoscout24.fr/offres/mini-one-d-1-5-navi-clim-start-stop-euro-6b-diesel-noir-d19fe6c5-3a03-4c25-aef0-460b3849539e",
    "prix": "€ 6 750",
    "marque": "MINI One D1.5 Navi Clim Start&Stop Euro 6b",
    "localisation": "6150 Anderlues",
    "kilometrage": 152600,
    "annee": 2016,
    "carburant": "Diesel",
    "boite_de_vitesse": "Manuelle",
    "transmission": "Avant",
    "puissance": "70 kW (95 CH)",
    "type_de_vehicule": "Berline",
    "sieges": 4,
    "portes": 3
  },
  {
    "lien_fiche": "https://www.autoscout24.fr/offres/peugeot-308-sw-1-2-pur-style-camera-parks-trekh-navi-apk-nap-essence-noir-4874c058-e02a-4544-9924-0f0c9f834aa6",
    "prix": "€ 4 999",
    "marque": "Peugeot 308SW 1.2 Pur Style/CAMERA/PARKS/TREKH/NAVI/APK/NAP",
    "localisation": "4264 KM VEEN",
    "kilometrage": 159475,
    "annee": 2016,
    "carburant": "Essence",
    "boite_de_vitesse": "Manuelle",
    "transmission": "Avant",
    "puissance": "81 kW (110 CH)",
    "type_de_vehicule": "Break",
    "sieges": 5,
    "portes": 5
  },
  {
    "lien_fiche": "https://www.autoscout24.fr/offres/hyundai-ix35-2-0-crdi-hp-4wd-dynamic-aut-apk-clima-pano-diesel-noir-4e7bcb72-8c0c-4ed3-8a78-485280631051",
    "prix": "€ 5 950",
    "marque": "Hyundai iX352.0 CRDi HP 4WD Dynamic AUT/APK/CLIMA/PANO",
    "localisation": "7091 EP DINXPERLO",
    "kilometrage": 170884,
    "annee": 2011,
    "carburant": "Diesel",
    "boite_de_vitesse": "Automatique",
    "transmission": "Avant",
    "puissance": "135 kW (184 CH)",
    "type_de_vehicule": "SUV/4x4/Pick-Up",
    "sieges": 5,
    "portes": 5
  },
  {
    "lien_fiche": "https://www.autoscout24.fr/offres/volkswagen-golf-5p-1-6-tdi-comfortline-diesel-a1816cdf-881a-45f8-b0e2-fedd99d6501e",
    "prix": "€ 5 490",
    "marque": "Volkswagen Golf5p 1.6 tdi Comfortline",
    "localisation": "00133 Roma - RM",
    "kilometrage": 150000,
    "annee": 2012,
    "carburant": "Diesel",
    "boite_de_vitesse": "Manuelle",
    "transmission": "Avant",
    "puissance": "77 kW (105 CH)",
    "type_de_vehicule": "Berline",
    "sieges": 5,
    "portes": 5
  },
  {
    "lien_fiche": "https://www.autoscout24.fr/offres/mercedes-benz-e-350-bluetec-pdc-schiebedach-leder-navi-diesel-brun-a6ab1703-8814-4742-a514-8fd5aa65a7b9",
    "prix": "€ 8 990",
    "marque": "Mercedes-Benz E 350BlueTec PDC. Schiebedach. Leder. Navi",
    "localisation": "55128 Mainz",
    "kilometrage": 137900,
    "annee": 2010,
    "carburant": "Diesel",
    "boite_de_vitesse": "Automatique",
    "transmission": "Arrière",
    "puissance": "155 kW (211 CH)",
    "type_de_vehicule": "Berline",
    "sieges": 5,
    "portes": 4
  },
  {
    "lien_fiche": "https://www.autoscout24.fr/offres/ford-fiesta-trend-essence-bleu-2d3ac094-0d43-482a-98f3-7db4d25cf2d1",
    "prix": "€ 1 900",
    "marque": "Ford FiestaTrend",
    "localisation": "65428 Rüsselsheim",
    "kilometrage": 199890,
    "annee": 2011,
    "carburant": "Essence",
    "boite_de_vitesse": "Manuelle",
    "transmission": "Avant",
    "puissance": "60 kW (82 CH)",
    "type_de_vehicule": "Citadine",
    "sieges": 5,
    "portes": 4
  },
  {
    "lien_fiche": "https://www.autoscout24.fr/offres/mini-cooper-clubman-cooper-clubman-chili-pan-dach-ohne-tuev-essence-brun-4a25cdaa-2197-4c2c-a068-05c5e89b687c",
    "prix": "€ 1 950",
    "marque": "MINI Cooper ClubmanCOOPER Clubman Chili*PAN-DACH*OHNE TÜV*",
    "localisation": "14480 Potsdam",
    "kilometrage": 200000,
    "annee": 2008,
    "carburant": "Essence",
    "boite_de_vitesse": "Manuelle",
    "transmission": "Avant",
    "puissance": "88 kW (120 CH)",
    "type_de_vehicule": "Break",
    "sieges": null,
    "portes": 4
  },
  {
    "lien_fiche": "https://www.autoscout24.fr/offres/opel-crossland-x-crossland-x-1-6-cdti-blueinjec-ecotec-edition-s-s-diesel-bleu-837e94f0-710d-41bd-936c-d13a0b133f9b",
    "prix": "€ 7 990",
    "marque": "Opel Crossland XCrossland X 1.6 CDTI Blueinjec.ECOTEC Edition S/S",
    "localisation": "5600 Mariembourg",
    "kilometrage": 139000,
    "annee": 2017,
    "carburant": "Diesel",
    "boite_de_vitesse": "Manuelle",
    "transmission": "Avant",
    "puissance": "73 kW (99 CH)",
    "type_de_vehicule": "SUV/4x4/Pick-Up",
    "sieges": 5,
    "portes": 5
  },
  {
    "lien_fiche": "https://www.autoscout24.fr/offres/jaguar-e-pace-2-0d-i4-s-awd-180cv-auto-diesel-blanc-fe4093cc-ea10-4905-a9af-576c2f88d89d",
    "prix": "€ 13 200",
    "marque": "Jaguar E-Pace2.0d i4 S awd 180cv auto",
    "localisation": "20064 Gorgonzola - Milano - MI",
    "kilometrage": 157000,
    "annee": 2018,
    "carburant": "Diesel",
    "boite_de_vitesse": "Automatique",
    "transmission": "Avant",
    "puissance": "132 kW (179 CH)",
    "type_de_vehicule": "SUV/4x4/Pick-Up",
    "sieges": 5,
    "portes": 5
  },
  {
    "lien_fiche": "https://www.autoscout24.fr/offres/volkswagen-golf-comfortline-tsi-essence-rouge-9f033666-57cf-4fc0-87ff-021ef29cdba3",
    "prix": "€ 6 999",
    "marque": "Volkswagen GolfComfortline TSI",
    "localisation": "4150 Rohrbach",
    "kilometrage": 142000,
    "annee": 2015,
    "carburant": "Essence",
    "boite_de_vitesse": "Manuelle",
    "transmission": "Avant",
    "puissance": "63 kW (86 CH)",
    "type_de_vehicule": "Berline",
    "sieges": 5,
    "portes": 5
  },
  {
    "lien_fiche": "https://www.autoscout24.fr/offres/ford-kuga-2-0-tdci-titanium-4x4-aut-diesel-blanc-dd08ce7b-ebc4-4f70-b02e-5a1b272eb013",
    "prix": "€ 7 900",
    "marque": "Ford Kuga2,0 TDCi Titanium 4x4 Aut.",
    "localisation": null,
    "kilometrage": 129000,
    "annee": 2014,
    "carburant": "Diesel",
    "boite_de_vitesse": "Automatique",
    "transmission": "Avant",
    "puissance": "103 kW (140 CH)",
    "type_de_vehicule": "SUV/4x4/Pick-Up",
    "sieges": 5,
    "portes": 5
  },
  {
    "lien_fiche": "https://www.autoscout24.fr/offres/peugeot-207-sw-1-4-vti-blue-lease-essence-noir-b59d5ad3-2214-43ad-9de8-bbf29c39a325",
    "prix": "€ 1 949",
    "marque": "Peugeot 207SW 1.4 VTi Blue Lease",
    "localisation": "3771 AG BARNEVELD",
    "kilometrage": 147701,
    "annee": 2011,
    "carburant": "Essence",
    "boite_de_vitesse": "Manuelle",
    "transmission": "Avant",
    "puissance": "71 kW (97 CH)",
    "type_de_vehicule": "Break",
    "sieges": 5,
    "portes": 5
  },
  {
    "lien_fiche": "https://www.autoscout24.fr/offres/seat-ibiza-1-4-sport-up-apk-01-2027-essence-gris-86e7b7b5-47ed-4a82-b6fb-ab45d9b5e642",
    "prix": "€ 1 949",
    "marque": "SEAT Ibiza1.4 Sport-up. APK 01-2027!",
    "localisation": "3771 AG BARNEVELD",
    "kilometrage": 255429,
    "annee": 2027,
    "carburant": "Essence",
    "boite_de_vitesse": "Manuelle",
    "transmission": "Avant",
    "puissance": "63 kW (86 CH)",
    "type_de_vehicule": "Citadine",
    "sieges": 5,
    "portes": 5
  },
  {
    "lien_fiche": "https://www.autoscout24.fr/offres/renault-clio-1-2i-ice-watch-1er-propretaire-eerste-eig-essence-a3225578-fb3d-4a48-addf-abbdd14b6199",
    "prix": "€ 4 300",
    "marque": "Renault Clio1.2i Ice-Watch / 1er Propretaire / Eerste Eig.",
    "localisation": "1853 Grimbergen",
    "kilometrage": 60000,
    "annee": 2012,
    "carburant": "Essence",
    "boite_de_vitesse": "Manuelle",
    "transmission": "Arrière",
    "puissance": "55 kW (75 CH)",
    "type_de_vehicule": "Berline",
    "sieges": 5,
    "portes": 5
  },
  {
    "lien_fiche": "https://www.autoscout24.fr/offres/nissan-juke-juke-i-2010-1-5-dci-visia-no-garanzia-diesel-blanc-02222ee5-f0d8-4415-827d-0cfdd36b84cb",
    "prix": "€ 3 990",
    "marque": "Nissan JukeJuke I 2010 1.5 dci Visia NO ...GARANZIA...!!!!",
    "localisation": "20155 Milano - MI",
    "kilometrage": 190000,
    "annee": 2010,
    "carburant": "Diesel",
    "boite_de_vitesse": "Manuelle",
    "transmission": "Avant",
    "puissance": "81 kW (110 CH)",
    "type_de_vehicule": "SUV/4x4/Pick-Up",
    "sieges": 5,
    "portes": 5
  },
  {
    "lien_fiche": "https://www.autoscout24.fr/offres/lancia-ypsilon-1-2-8v-platinum-69cv-essence-6b02274f-0811-4fe2-9dce-58746dca4dc4",
    "prix": "€ 3 490",
    "marque": "Lancia Ypsilon1.2 8v Platinum 69cv",
    "localisation": "21046 Malnate - Varese - VA",
    "kilometrage": 106426,
    "annee": 2011,
    "carburant": "Essence",
    "boite_de_vitesse": "Manuelle",
    "transmission": "Avant",
    "puissance": "51 kW (69 CH)",
    "type_de_vehicule": "Berline",
    "sieges": 4,
    "portes": 3
  },
  {
    "lien_fiche": "https://www.autoscout24.fr/offres/mitsubishi-space-star-1-2-intense-sda-essence-blanc-adcdfa7a-9572-420d-949b-0b14d3fd210f",
    "prix": "€ 8 900",
    "marque": "Mitsubishi Space Star1.2 Intense SDA",
    "localisation": "10044 Pianezza - Torino - To",
    "kilometrage": 22715,
    "annee": 2023,
    "carburant": "Essence",
    "boite_de_vitesse": "Manuelle",
    "transmission": "Avant",
    "puissance": "52 kW (71 CH)",
    "type_de_vehicule": "Berline",
    "sieges": 5,
    "portes": 5
  },
  {
    "lien_fiche": "https://www.autoscout24.fr/offres/skoda-octavia-combi-style-euro6-klimaaut-pano-navi-essence-gris-2746b6b1-07c5-46e3-bdcf-52da2a0c29d6",
    "prix": "€ 4 398",
    "marque": "Skoda OctaviaCombi Style Euro6,Klimaaut.,Pano,Navi,",
    "localisation": "41836 Hückelhoven",
    "kilometrage": 269622,
    "annee": 2017,
    "carburant": "Essence",
    "boite_de_vitesse": "Manuelle",
    "transmission": "Avant",
    "puissance": "85 kW (116 CH)",
    "type_de_vehicule": "Break",
    "sieges": 5,
    "portes": 4
  },
  {
    "lien_fiche": "https://www.autoscout24.fr/offres/toyota-aygo-aygo-1-0i-vvt-i-essence-gris-f6589099-3133-4763-9851-83cca9593c41",
    "prix": "€ 2 600",
    "marque": "Toyota AygoAygo 1.0i VVT-i",
    "localisation": "4432 Alleur",
    "kilometrage": 144327,
    "annee": 2006,
    "carburant": "Essence",
    "boite_de_vitesse": "Manuelle",
    "transmission": "Arrière",
    "puissance": "50 kW (68 CH)",
    "type_de_vehicule": "Berline",
    "sieges": 5,
    "portes": 3
  },
  {
    "lien_fiche": "https://www.autoscout24.fr/offres/volkswagen-golf-variant-sw-1-6-cr-tdi-trendline-1hnd-carpass-carnet-diesel-argent-032f876c-bba3-4fe8-b819-b460f46656d3",
    "prix": "€ 10 650",
    "marque": "Volkswagen Golf VariantSW 1.6 CR TDi Trendline 1HND CarPass Carnet",
    "localisation": "1760 Roosdaal",
    "kilometrage": 105000,
    "annee": null,
    "carburant": "Diesel",
    "boite_de_vitesse": "Manuelle",
    "transmission": "Avant",
    "puissance": "81 kW (110 CH)",
    "type_de_vehicule": "Break",
    "sieges": 5,
    "portes": 5
  },
  {
    "lien_fiche": "https://www.autoscout24.fr/offres/audi-a4-lim-2-0-essence-argent-355e89de-b3ac-4a71-8513-a9405d6efc5d",
    "prix": "€ 2 990",
    "marque": "Audi A4Lim. 2.0",
    "localisation": "25451 Quickborn",
    "kilometrage": 180000,
    "annee": 2005,
    "carburant": "Essence",
    "boite_de_vitesse": "Automatique",
    "transmission": "Avant",
    "puissance": "96 kW (131 CH)",
    "type_de_vehicule": "Berline",
    "sieges": 5,
    "portes": 4
  },
  {
    "lien_fiche": "https://www.autoscout24.fr/offres/fiat-500-500-1-2-lounge-essence-noir-977feb9e-3cfe-415f-a626-acfce238169c",
    "prix": "€ 5 500",
    "marque": "Fiat 500500 1.2 Lounge",
    "localisation": "20138 Muggiò - Monza Brianza - MB",
    "kilometrage": 92000,
    "annee": null,
    "carburant": "Essence",
    "boite_de_vitesse": "Automatique",
    "transmission": "Avant",
    "puissance": "51 kW (69 CH)",
    "type_de_vehicule": "Berline",
    "sieges": 4,
    "portes": 3
  },
  {
    "lien_fiche": "https://www.autoscout24.fr/offres/nissan-qashqai-1-5-dci-360-110cv-navi-camera-km-87000-diesel-gris-504e8fad-29a0-400d-be03-d1827d882490",
    "prix": "€ 9 800",
    "marque": "Nissan Qashqai1.5 dci 360 110cv NAVI CAMERA KM 87000",
    "localisation": "20855 Lesmo - Monza Brianza -  MB",
    "kilometrage": null,
    "annee": null,
    "carburant": "Diesel",
    "boite_de_vitesse": "Manuelle",
    "transmission": "Avant",
    "puissance": "81 kW (110 CH)",
    "type_de_vehicule": "SUV/4x4/Pick-Up",
    "sieges": 5,
    "portes": 5
  },
  {
    "lien_fiche": "https://www.autoscout24.fr/offres/mercedes-benz-c-220-c-klasse-t-modell-c-220-t-cdi-diesel-noir-d046f658-36ae-4fd6-8158-f01291761057",
    "prix": "€ 4 200",
    "marque": "Mercedes-Benz C 220C -Klasse T-Modell C 220 T CDI",
    "localisation": "99947 Bad Langensalza",
    "kilometrage": 503735,
    "annee": 2013,
    "carburant": "Diesel",
    "boite_de_vitesse": "Automatique",
    "transmission": "Avant",
    "puissance": "125 kW (170 CH)",
    "type_de_vehicule": "Break",
    "sieges": 5,
    "portes": 4
  },
  {
    "lien_fiche": "https://www.autoscout24.fr/offres/volkswagen-passat-lim-comfortline-17zoll-klima-tempo-essence-gris-08530f11-7512-4ca5-a47b-cbc47e9d1263",
    "prix": "€ 2 900",
    "marque": "Volkswagen PassatLim. Comfortline*17ZOLL*KLIMA*TEMPO*",
    "localisation": "12353 Berlin",
    "kilometrage": 132833,
    "annee": 2005,
    "carburant": "Essence",
    "boite_de_vitesse": "Manuelle",
    "transmission": "Avant",
    "puissance": "85 kW (116 CH)",
    "type_de_vehicule": "Berline",
    "sieges": 5,
    "portes": 4
  },
  {
    "lien_fiche": "https://www.autoscout24.fr/offres/omoda-5-1-6-tgdi-147cv-aut-anniversary-pure-promo-essence-ba399de0-13eb-49b4-92f9-d2f0acdf9886",
    "prix": "€ 22 990",
    "marque": "Omoda 51.6 TGDI 147CV AUT. ANNIVERSARY PURE *PROMO*",
    "localisation": "20032 Cormano - Milano - MI",
    "kilometrage": 1,
    "annee": 2025,
    "carburant": "Essence",
    "boite_de_vitesse": "Automatique",
    "transmission": "Avant",
    "puissance": "108 kW (147 CH)",
    "type_de_vehicule": "SUV/4x4/Pick-Up",
    "sieges": 5,
    "portes": 5
  },
  {
    "lien_fiche": "https://www.autoscout24.fr/offres/fiat-grande-panda-grande-panda-1-2-hybrid-110-cv-icon-promo-flex-electrique-essence-noir-ea0d426d-d5ff-4f80-a5a6-db51a88722ce",
    "prix": "€ 15 490",
    "marque": "Fiat Grande PandaGrande Panda 1.2 Hybrid 110 CV Icon PROMO FLEX",
    "localisation": "10043 Orbassano - Torino - TO",
    "kilometrage": 10,
    "annee": 2026,
    "carburant": "Essence",
    "boite_de_vitesse": "Automatique",
    "transmission": "Avant",
    "puissance": "81 kW (110 CH)",
    "type_de_vehicule": "Berline",
    "sieges": 5,
    "portes": 5
  },
  {
    "lien_fiche": "https://www.autoscout24.fr/offres/alfa-romeo-giulietta-alfa-romeo-giulietta-1-6-jtdm-2-105-cv-exclusive-diesel-noir-f40f665a-60bd-48ac-b3fd-c0803210f733",
    "prix": "€ 5 300",
    "marque": "Alfa Romeo GiuliettaAlfa Romeo Giulietta 1.6 JTDm-2 105 CV Exclusive",
    "localisation": "10143 Torino - To",
    "kilometrage": 181000,
    "annee": null,
    "carburant": "Diesel",
    "boite_de_vitesse": "Manuelle",
    "transmission": "Avant",
    "puissance": "77 kW (105 CH)",
    "type_de_vehicule": "Berline",
    "sieges": 5,
    "portes": 5
  },
  {
    "lien_fiche": "https://www.autoscout24.fr/offres/dacia-sandero-ii-essential-1-hand-huneu-klima-8-fach-essence-noir-3f1e73d1-54d6-44d0-b36e-38b6d16443f6",
    "prix": "€ 5 990",
    "marque": "Dacia SanderoII Essential 1.Hand*HUneu*Klima*8-fach",
    "localisation": "70329 Stuttgart",
    "kilometrage": 74000,
    "annee": 2018,
    "carburant": "Essence",
    "boite_de_vitesse": "Manuelle",
    "transmission": "Arrière",
    "puissance": "54 kW (73 CH)",
    "type_de_vehicule": "Berline",
    "sieges": 5,
    "portes": 5
  },
  {
    "lien_fiche": "https://www.autoscout24.fr/offres/audi-a5-coupe-3-0-tdi-s-tronic-s-line-virtual-cockpit-diesel-noir-312015b1-daaa-4da3-809f-397916cfa554",
    "prix": "€ 20 900",
    "marque": "Audi A5Coupé 3,0 TDI S-tronic | S-LINE | VIRTUAL -COCKPIT",
    "localisation": "4060 Leonding",
    "kilometrage": 89000,
    "annee": 2017,
    "carburant": "Diesel",
    "boite_de_vitesse": "Automatique",
    "transmission": "Avant",
    "puissance": "160 kW (218 CH)",
    "type_de_vehicule": "Coupé",
    "sieges": 5,
    "portes": 2
  },
  {
    "lien_fiche": "https://www.autoscout24.fr/offres/mercedes-benz-g-63-amg-g-63-amg-perform-carbon-a22-ride-my26-matt-essence-noir-9a1fb71d-86fa-497d-b591-6517ad209550",
    "prix": "€ 273 650",
    "marque": "Mercedes-Benz G 63 AMGG 63 *AMG Perform*Carbon*A22 RIDE*MY26*MATT",
    "localisation": "42857 Remscheid",
    "kilometrage": 70,
    "annee": null,
    "carburant": "Essence",
    "boite_de_vitesse": "Automatique",
    "transmission": "Avant",
    "puissance": "430 kW (585 CH)",
    "type_de_vehicule": "SUV/4x4/Pick-Up",
    "sieges": 5,
    "portes": 4
  },
  {
    "lien_fiche": "https://www.autoscout24.fr/offres/opel-corsa-gs-1-2-benzina-101cv-essence-argent-abaf9475-6514-4792-ab71-d6aa98b9b5a2",
    "prix": "€ 12 990",
    "marque": "Opel CorsaGS 1.2 Benzina 101CV",
    "localisation": "20092 Cinisello Balsamo  - Milano - MI",
    "kilometrage": 9448,
    "annee": null,
    "carburant": "Essence",
    "boite_de_vitesse": "Manuelle",
    "transmission": "Avant",
    "puissance": "74 kW (101 CH)",
    "type_de_vehicule": "Citadine",
    "sieges": 5,
    "portes": 5
  },
  {
    "lien_fiche": "https://www.autoscout24.fr/offres/volkswagen-golf-vi-match-neu-steuerkette-12-monat-garantie-essence-blanc-6e0b9c8c-9ebd-4908-ac62-d90fbe5df919",
    "prix": "€ 6 390",
    "marque": "Volkswagen GolfVI Match*Neu Steuerkette* 12 Monat Garantie",
    "localisation": "64546 Walldorf",
    "kilometrage": 142920,
    "annee": 2012,
    "carburant": "Essence",
    "boite_de_vitesse": "Manuelle",
    "transmission": "Avant",
    "puissance": "77 kW (105 CH)",
    "type_de_vehicule": "Berline",
    "sieges": 5,
    "portes": 2
  },
  {
    "lien_fiche": "https://www.autoscout24.fr/offres/renault-clio-eco-g-100-cv-gpl-blanc-f89bfc07-e438-4958-b2c2-147a9b695fe4",
    "prix": "€ 13 900",
    "marque": "Renault ClioECO-G 100 CV",
    "localisation": "10126 Torino - TO",
    "kilometrage": 7,
    "annee": 2025,
    "carburant": "Électrique",
    "boite_de_vitesse": "Manuelle",
    "transmission": "Avant",
    "puissance": "74 kW (101 CH)",
    "type_de_vehicule": "Berline",
    "sieges": 5,
    "portes": 5
  },
  {
    "lien_fiche": "https://www.autoscout24.fr/offres/opel-insignia-2-0-t-executive-navi-cruise-ecc-leer-stoelverwarmi-essence-noir-8845a939-e5dd-4bee-a0ba-bb11ec004e83",
    "prix": "€ 6 500",
    "marque": "Opel Insignia2.0 T Executive NAVI CRUISE ECC LEER STOELVERWARMI",
    "localisation": "9502 EZ STADSKANAAL",
    "kilometrage": 180509,
    "annee": 2009,
    "carburant": "Essence",
    "boite_de_vitesse": "Automatique",
    "transmission": "Avant",
    "puissance": "162 kW (220 CH)",
    "type_de_vehicule": "Berline",
    "sieges": 5,
    "portes": 4
  },
  {
    "lien_fiche": "https://www.autoscout24.fr/offres/jaguar-e-pace-e-pace-d150-navi-cruisec-elek-z-leder-garantie-diesel-noir-6c14b1c8-ce2d-41aa-a80d-81664ca2eb72",
    "prix": "€ 16 599",
    "marque": "Jaguar E-PaceE-Pace D150 Navi CruiseC Elek. Z. Leder Garantie*",
    "localisation": "3530 Houthalen-Helchteren",
    "kilometrage": 81258,
    "annee": 2020,
    "carburant": "Diesel",
    "boite_de_vitesse": "Manuelle",
    "transmission": "Avant",
    "puissance": "110 kW (150 CH)",
    "type_de_vehicule": "SUV/4x4/Pick-Up",
    "sieges": 5,
    "portes": 5
  },
  {
    "lien_fiche": "https://www.autoscout24.fr/offres/opel-astra-h-1-8-lim-automatik-cosmo-essence-noir-6eeaef50-e680-4b75-aacb-31ed7fff3265",
    "prix": "€ 3 499",
    "marque": "Opel AstraH 1.8 Lim. Automatik Cosmo",
    "localisation": "06796 Sandersdorf-Brehna",
    "kilometrage": 102113,
    "annee": 2008,
    "carburant": "Essence",
    "boite_de_vitesse": "Automatique",
    "transmission": "Arrière",
    "puissance": "103 kW (140 CH)",
    "type_de_vehicule": "Berline",
    "sieges": 5,
    "portes": 4
  },
  {
    "lien_fiche": "https://www.autoscout24.fr/offres/volkswagen-golf-golf-1-4i-51-000-km-1-eigenaar-carplay-bluetooth-essence-argent-f4d3e63e-a42a-4f53-8715-9a82669ebd54",
    "prix": "€ 7 290",
    "marque": "Volkswagen GolfGolf 1.4i/ 51.000 km!/1 Eigenaar/Carplay/Bluetooth",
    "localisation": "1480 Tubize / Tubeke",
    "kilometrage": 0,
    "annee": 2010,
    "carburant": "Essence",
    "boite_de_vitesse": "Manuelle",
    "transmission": "Avant",
    "puissance": "59 kW (80 CH)",
    "type_de_vehicule": "Berline",
    "sieges": 5,
    "portes": 5
  },
  {
    "lien_fiche": "https://www.autoscout24.fr/offres/nissan-note-1-6i-euro-5-boite-auto-navigation-carnet-essence-rouge-579190e8-0199-4f2c-91c2-0d6a20d5430b",
    "prix": "€ 4 250",
    "marque": "Nissan Note1.6i Euro 5 - Boite Auto - Navigation - Carnet",
    "localisation": "6031 Charleroi",
    "kilometrage": 177429,
    "annee": 2012,
    "carburant": "Essence",
    "boite_de_vitesse": "Automatique",
    "transmission": "Avant",
    "puissance": "81 kW (110 CH)",
    "type_de_vehicule": "Monospace",
    "sieges": 5,
    "portes": 5
  },
  {
    "lien_fiche": "https://www.autoscout24.fr/offres/fiat-500l-lounge-diesel-gris-ad2a95eb-d32c-45f0-9a89-24837c4c2006",
    "prix": "€ 6 980",
    "marque": "Fiat 500LLounge",
    "localisation": "36419 Geisa",
    "kilometrage": 93324,
    "annee": 2016,
    "carburant": "Diesel",
    "boite_de_vitesse": "Manuelle",
    "transmission": "Avant",
    "puissance": "88 kW (120 CH)",
    "type_de_vehicule": "SUV/4x4/Pick-Up",
    "sieges": 5,
    "portes": 4
  },
  {
    "lien_fiche": "https://www.autoscout24.fr/offres/chevrolet-kalos-1-4-sx-automatik-essence-15c72005-f212-4840-b287-d4f60141f658",
    "prix": "€ 3 199",
    "marque": "Chevrolet Kalos1.4 SX Automatik",
    "localisation": "01159 Dresden",
    "kilometrage": 59000,
    "annee": 2007,
    "carburant": "Essence",
    "boite_de_vitesse": "Automatique",
    "transmission": "Avant",
    "puissance": "69 kW (94 CH)",
    "type_de_vehicule": "Berline",
    "sieges": 5,
    "portes": 4
  },
  {
    "lien_fiche": "https://www.autoscout24.fr/offres/peugeot-308-peugeot-308-allure-1-hand-zahnriemen-tuev-essence-gris-92c3150e-ba5c-40eb-910b-28b09b7768cd",
    "prix": "€ 8 390",
    "marque": "Peugeot 308Peugeot 308 Allure | 1.Hand | Zahnriemen & TÜV",
    "localisation": "56220 Urmitz",
    "kilometrage": 88933,
    "annee": 2016,
    "carburant": "Essence",
    "boite_de_vitesse": "Manuelle",
    "transmission": "Avant",
    "puissance": "96 kW (131 CH)",
    "type_de_vehicule": "Citadine",
    "sieges": 5,
    "portes": 5
  },
  {
    "lien_fiche": "https://www.autoscout24.fr/offres/saab-9-3-sport-sedan-1-8t-arc-ecc-audio-cd-leder-elect-pak-essence-gris-8bf3aa8e-3b91-47fa-a8b5-b60dd45b1707",
    "prix": "€ 1 749",
    "marque": "Saab 9-3Sport Sedan 1.8t Arc ECC Audio/CD Leder Elect. pak",
    "localisation": "1746 CM DIRKSHORN",
    "kilometrage": 332120,
    "annee": 2005,
    "carburant": "Essence",
    "boite_de_vitesse": "Manuelle",
    "transmission": "Avant",
    "puissance": "110 kW (150 CH)",
    "type_de_vehicule": "Berline",
    "sieges": 5,
    "portes": 4
  },
  {
    "lien_fiche": "https://www.autoscout24.fr/offres/opel-zafira-edition-aut-tempomat-pdc-alu-shz-klima-essence-argent-539ce5a8-3f6a-49af-809c-60ddf53d5529",
    "prix": "€ 3 440",
    "marque": "Opel ZafiraEdition Aut. Tempomat*PDC*Alu*Shz*Klima",
    "localisation": "90556 Cadolzburg",
    "kilometrage": 156448,
    "annee": 2012,
    "carburant": "Essence",
    "boite_de_vitesse": "Automatique",
    "transmission": "Avant",
    "puissance": "103 kW (140 CH)",
    "type_de_vehicule": "Monospace",
    "sieges": 5,
    "portes": 4
  },
  {
    "lien_fiche": "https://www.autoscout24.fr/offres/volvo-v40-2-0-d2-eco-gps-cuir-city-safety-cruise-sensor-clim-diesel-b7553f17-0bbf-4e9b-bd60-731c964bff57",
    "prix": "€ 10 990",
    "marque": "Volvo V402.0 D2 Eco Gps Cuir City Safety Cruise Sensor Clim",
    "localisation": "6200 Chatelet",
    "kilometrage": 92105,
    "annee": 2017,
    "carburant": "Diesel",
    "boite_de_vitesse": "Manuelle",
    "transmission": "Avant",
    "puissance": "88 kW (120 CH)",
    "type_de_vehicule": "Berline",
    "sieges": 5,
    "portes": 5
  },
  {
    "lien_fiche": "https://www.autoscout24.fr/offres/peugeot-3008-1-6-vti-premiere-ecc-audio-cd-mp3-lmv-17-esp-pdc-essence-bleu-8e42046e-8eec-4f11-ba80-7d7e1f437c6a",
    "prix": "€ 2 749",
    "marque": "Peugeot 30081.6 VTi Première ECC Audio-CD/MP3 LMV 17\" ESP PDC",
    "localisation": "1746 CM DIRKSHORN",
    "kilometrage": 175131,
    "annee": null,
    "carburant": "Essence",
    "boite_de_vitesse": "Manuelle",
    "transmission": "Avant",
    "puissance": "88 kW (120 CH)",
    "type_de_vehicule": "Monospace",
    "sieges": 5,
    "portes": 5
  },
  {
    "lien_fiche": "https://www.autoscout24.fr/offres/volkswagen-golf-tdi-diesel-noir-ab13b365-c6f7-4014-9948-058c3ff23a86",
    "prix": "€ 6 999",
    "marque": "Volkswagen GolfTDI",
    "localisation": "4150 Rohrbach",
    "kilometrage": 181000,
    "annee": 2013,
    "carburant": "Diesel",
    "boite_de_vitesse": "Manuelle",
    "transmission": "Avant",
    "puissance": "77 kW (105 CH)",
    "type_de_vehicule": "Berline",
    "sieges": 5,
    "portes": 3
  },
  {
    "lien_fiche": "https://www.autoscout24.fr/offres/hyundai-santa-fe-shine-4wd-auto-diesel-gris-9b8c71a9-ac76-4204-8f2a-46d2c8157e97",
    "prix": "€ 24 490",
    "marque": "Hyundai SANTA FEShine 4WD AUTO",
    "localisation": "4040 Herstal",
    "kilometrage": 64789,
    "annee": 2020,
    "carburant": "Diesel",
    "boite_de_vitesse": "Automatique",
    "transmission": "Avant",
    "puissance": "147 kW (200 CH)",
    "type_de_vehicule": "SUV/4x4/Pick-Up",
    "sieges": 5,
    "portes": 5
  },
  {
    "lien_fiche": "https://www.autoscout24.fr/offres/fiat-panda-1-2-dynamic-69cv-e5-essence-argent-6fadf6e0-3c7c-4c09-af42-9a28044e6ab8",
    "prix": "€ 4 400",
    "marque": "Fiat Panda1.2 Dynamic 69cv E5",
    "localisation": "14040 Castelnuovo Calcea - AT",
    "kilometrage": 73162,
    "annee": 2010,
    "carburant": "Essence",
    "boite_de_vitesse": "Manuelle",
    "transmission": "Avant",
    "puissance": "51 kW (69 CH)",
    "type_de_vehicule": "Citadine",
    "sieges": 4,
    "portes": 5
  },
  {
    "lien_fiche": "https://www.autoscout24.fr/offres/mini-one-1-6-essence-noir-4ac9e5e8-c2e3-4a4b-b4d2-ddbbc64f8cf2",
    "prix": "€ 4 990",
    "marque": "MINI One1,6",
    "localisation": "4020 Linz",
    "kilometrage": 96000,
    "annee": 2011,
    "carburant": "Essence",
    "boite_de_vitesse": "Manuelle",
    "transmission": "Avant",
    "puissance": "72 kW (98 CH)",
    "type_de_vehicule": "Berline",
    "sieges": 4,
    "portes": 3
  },
  {
    "lien_fiche": "https://www.autoscout24.fr/offres/fiat-500-1-2-sport-pano-essence-rouge-516f93af-fbcc-4614-a69e-3369f3334ad1",
    "prix": "€ 2 499",
    "marque": "Fiat 5001.2 Sport |Pano|",
    "localisation": "4905 AA OOSTERHOUT",
    "kilometrage": 172606,
    "annee": null,
    "carburant": "Essence",
    "boite_de_vitesse": "Manuelle",
    "transmission": "Avant",
    "puissance": "51 kW (69 CH)",
    "type_de_vehicule": "Citadine",
    "sieges": 4,
    "portes": 3
  },
  {
    "lien_fiche": "https://www.autoscout24.fr/offres/mini-one-cabrio-mini-one-benzina-1-6-sidewalk-cabrio-essence-blanc-80156ef2-5ec2-4353-b511-f01c2ba1375d",
    "prix": "€ 3 700",
    "marque": "MINI One Cabriomini one benzina 1.6 Sidewalk cabrio",
    "localisation": "22070 Guanzate - Como - Co",
    "kilometrage": 125000,
    "annee": 2007,
    "carburant": "Essence",
    "boite_de_vitesse": "Manuelle",
    "transmission": "Arrière",
    "puissance": "66 kW (90 CH)",
    "type_de_vehicule": "Cabriolet",
    "sieges": 4,
    "portes": 2
  },
  {
    "lien_fiche": "https://www.autoscout24.fr/offres/audi-a4-a4-avant-2-0-tdi-s-line-diesel-noir-cc67ab9b-dd20-45a1-85be-d4a5d0da7134",
    "prix": "€ 10 990",
    "marque": "Audi A4A4 Avant 2.0 TDi S line",
    "localisation": "6061 Montignies sur Sambre",
    "kilometrage": 140724,
    "annee": 2014,
    "carburant": "Diesel",
    "boite_de_vitesse": "Manuelle",
    "transmission": "Avant",
    "puissance": "100 kW (136 CH)",
    "type_de_vehicule": "Break",
    "sieges": 5,
    "portes": 5
  },
  {
    "lien_fiche": "https://www.autoscout24.fr/offres/volkswagen-polo-1-0-tsi-comfortline-adaptief-cruise-69000-km-essence-blanc-ffc6c55a-ddaa-4507-81b5-ccc556e3440b",
    "prix": "€ 12 500",
    "marque": "Volkswagen Polo1.0 TSI Comfortline ADAPTIEF CRUISE 69000 KM.",
    "localisation": "9502 EZ STADSKANAAL",
    "kilometrage": 69000,
    "annee": null,
    "carburant": "Essence",
    "boite_de_vitesse": "Manuelle",
    "transmission": "Avant",
    "puissance": "70 kW (95 CH)",
    "type_de_vehicule": "Citadine",
    "sieges": 5,
    "portes": 5
  },
  {
    "lien_fiche": "https://www.autoscout24.fr/offres/dacia-duster-1-6-ice-4x2-ahk-klima-bluetooth-aux-usb-essence-blanc-da91ca1e-ef8a-4cd7-9f6f-1e8bb4a14d21",
    "prix": "€ 6 890",
    "marque": "Dacia Duster1.6 Ice 4x2 AHK Klima Bluetooth AUX USB",
    "localisation": "06796 Sandersdorf-Brehna",
    "kilometrage": 83653,
    "annee": 2014,
    "carburant": "Essence",
    "boite_de_vitesse": "Manuelle",
    "transmission": "Boîte manuelle",
    "puissance": "77 kW (105 CH)",
    "type_de_vehicule": "SUV/4x4/Pick-Up",
    "sieges": 5,
    "portes": 4
  },
  {
    "lien_fiche": "https://www.autoscout24.fr/offres/volkswagen-golf-variant-golf-variant-1-6-tdi-business-115cv-diesel-gris-2a115c72-197c-4c04-bd67-75d1bf702447",
    "prix": "€ 11 500",
    "marque": "Volkswagen Golf VariantGolf Variant 1.6 tdi Business 115cv",
    "localisation": "36040 Sarego - Vicenza - VI",
    "kilometrage": 117000,
    "annee": 2020,
    "carburant": "Diesel",
    "boite_de_vitesse": "Manuelle",
    "transmission": "Avant",
    "puissance": "85 kW (116 CH)",
    "type_de_vehicule": "Break",
    "sieges": 5,
    "portes": 5
  },
  {
    "lien_fiche": "https://www.autoscout24.fr/offres/volkswagen-polo-1-0-tsi-comfortline-navi-carplay-acc-bluetoo-essence-noir-1873bc4e-a499-4b34-bdfc-3e878f82926f",
    "prix": "€ 12 999",
    "marque": "Volkswagen Polo1.0 TSI Comfortline NAVI / CARPLAY / ACC / BLUETOO",
    "localisation": "8711 HP WORKUM",
    "kilometrage": 80294,
    "annee": 2020,
    "carburant": "Essence",
    "boite_de_vitesse": "Manuelle",
    "transmission": "Avant",
    "puissance": "70 kW (95 CH)",
    "type_de_vehicule": "Citadine",
    "sieges": 5,
    "portes": 5
  },
  {
    "lien_fiche": "https://www.autoscout24.fr/offres/seat-ibiza-ibiza-1-4i-style-garantie-1-an--essence-noir-b54b9e07-5655-452d-8660-48e75f25b2ed",
    "prix": "€ 5 495",
    "marque": "SEAT IbizaIbiza 1.4i Style | GARANTIE 1 AN ✅",
    "localisation": "4140 Sprimont",
    "kilometrage": 97856,
    "annee": 2011,
    "carburant": "Essence",
    "boite_de_vitesse": "Manuelle",
    "transmission": "Avant",
    "puissance": "63 kW (86 CH)",
    "type_de_vehicule": "Berline",
    "sieges": 5,
    "portes": 5
  },
  {
    "lien_fiche": "https://www.autoscout24.fr/offres/opel-astra-j-lim-5-trg-sport-automatik-diesel-argent-6b893c9f-50f6-4bd5-a921-c8d1137026e6",
    "prix": "€ 3 600",
    "marque": "Opel AstraJ Lim. 5-trg. Sport Automatik",
    "localisation": "99947 Bad Langensalza",
    "kilometrage": 257933,
    "annee": 2010,
    "carburant": "Diesel",
    "boite_de_vitesse": "Automatique",
    "transmission": "Avant",
    "puissance": "118 kW (160 CH)",
    "type_de_vehicule": "Berline",
    "sieges": 5,
    "portes": 4
  },
  {
    "lien_fiche": "https://www.autoscout24.fr/offres/skoda-fabia-wagon-1-0-mpi-executive-75cv-essence-gris-57da5d8f-d2cb-48bc-b209-663667f19a4f",
    "prix": "€ 7 450",
    "marque": "Skoda FabiaWagon 1.0 mpi Executive 75cv",
    "localisation": "51100 Stradario 01117 - Pistoia",
    "kilometrage": 73851,
    "annee": null,
    "carburant": "Essence",
    "boite_de_vitesse": "Manuelle",
    "transmission": "Avant",
    "puissance": "55 kW (75 CH)",
    "type_de_vehicule": "Break",
    "sieges": 5,
    "portes": 5
  },
  {
    "lien_fiche": "https://www.autoscout24.fr/offres/bmw-118-d-5p-business-diesel-blanc-611f6784-aeb8-48e0-b322-da1f2bae432b",
    "prix": "€ 5 900",
    "marque": "BMW 118d 5p. Business",
    "localisation": "10147 Torino",
    "kilometrage": 250103,
    "annee": 2013,
    "carburant": "Diesel",
    "boite_de_vitesse": "Manuelle",
    "transmission": "Arrière",
    "puissance": "105 kW (143 CH)",
    "type_de_vehicule": "Berline",
    "sieges": 5,
    "portes": 5
  },
  {
    "lien_fiche": "https://www.autoscout24.fr/offres/opel-astra-h-1-8-kombi-automatikgetriebe-essence-argent-ced3606c-d575-4682-9851-ef78d3cf1315",
    "prix": "€ 1 499",
    "marque": "Opel AstraH 1.8 Kombi Automatikgetriebe",
    "localisation": "85662 Hohenbrunn",
    "kilometrage": 144000,
    "annee": 2006,
    "carburant": "Essence",
    "boite_de_vitesse": "Automatique",
    "transmission": "Avant",
    "puissance": "92 kW (125 CH)",
    "type_de_vehicule": "Break",
    "sieges": 5,
    "portes": 4
  },
  {
    "lien_fiche": "https://www.autoscout24.fr/offres/opel-corsa-corsa-1-2-elegance-essence-blanc-962b85f1-4e86-4920-9a46-6a44f98c59fe",
    "prix": "€ 10 900",
    "marque": "Opel CorsaCorsa 1.2 Elegance",
    "localisation": "10079 Mappano",
    "kilometrage": 17400,
    "annee": null,
    "carburant": "Essence",
    "boite_de_vitesse": "Manuelle",
    "transmission": "Avant",
    "puissance": "55 kW (75 CH)",
    "type_de_vehicule": "Berline",
    "sieges": 5,
    "portes": 5
  },
  {
    "lien_fiche": "https://www.autoscout24.fr/offres/opel-corsa-1-2-start-stop-edition-r-kam-180-grad-dab-efh-essence-noir-0a3c1377-9572-4ad5-8838-2d6d2b584300",
    "prix": "€ 11 990",
    "marque": "Opel Corsa1.2 Start/Stop Edition R-KAM 180-Grad DAB+ EFH",
    "localisation": "46539 Dinslaken",
    "kilometrage": 26314,
    "annee": 2023,
    "carburant": "Essence",
    "boite_de_vitesse": "Manuelle",
    "transmission": "Avant",
    "puissance": "55 kW (75 CH)",
    "type_de_vehicule": "Citadine",
    "sieges": 5,
    "portes": 5
  },
  {
    "lien_fiche": "https://www.autoscout24.fr/offres/audi-q8-e-tron-55-quattro-408pk-115kwh-s-line-matrix-cam-electrique-gris-26be4a06-9c65-4990-9f3b-f7c03c2eb5d0",
    "prix": "€ 60 995",
    "marque": "Audi Q8 e-tron55 QUATTRO 408pk * 115KWh * S-LINE * MATRIX * CAM*",
    "localisation": "2250 Olen",
    "kilometrage": 15709,
    "annee": null,
    "carburant": "Électrique",
    "boite_de_vitesse": "Automatique",
    "transmission": "Avant",
    "puissance": "300 kW (408 CH)",
    "type_de_vehicule": "SUV/4x4/Pick-Up",
    "sieges": 5,
    "portes": 5
  },
  {
    "lien_fiche": "https://www.autoscout24.fr/offres/opel-astra-j-lim-5-trg-energy-essence-gris-bb017f6d-dcd1-44fa-bd43-04a53f7a0bc4",
    "prix": "€ 3 299",
    "marque": "Opel AstraJ Lim. 5-trg. Energy",
    "localisation": "68775 Ketsch",
    "kilometrage": 218000,
    "annee": 2014,
    "carburant": "Essence",
    "boite_de_vitesse": "Manuelle",
    "transmission": "Avant",
    "puissance": "85 kW (116 CH)",
    "type_de_vehicule": "Berline",
    "sieges": 5,
    "portes": 4
  },
  {
    "lien_fiche": "https://www.autoscout24.fr/offres/suzuki-alto-hu-neu-service-neu-gewaehrleistung-1-jahr-essence-mauve-d18cf5f3-1ce5-4252-b0d6-a9bc5f2ae94d",
    "prix": "€ 3 890",
    "marque": "Suzuki AltoHU NEU * Service NEU * GEWÄHRLEISTUNG 1 JAHR",
    "localisation": "41334 Nettetal",
    "kilometrage": 100000,
    "annee": 2011,
    "carburant": "Essence",
    "boite_de_vitesse": "Manuelle",
    "transmission": "Avant",
    "puissance": "50 kW (68 CH)",
    "type_de_vehicule": "Citadine",
    "sieges": 4,
    "portes": 5
  },
  {
    "lien_fiche": "https://www.autoscout24.fr/offres/fiat-500l-fiat-500l-1-4-95-cv-lounge-unicoproprietario-essence-a0531a9a-4ee7-49d4-bd6f-f96662015d8b",
    "prix": "€ 6 900",
    "marque": "Fiat 500LFIAT 500L 1.4 95 CV Lounge Unicoproprietario",
    "localisation": "10143 Torino - To",
    "kilometrage": 112000,
    "annee": null,
    "carburant": "Essence",
    "boite_de_vitesse": "Manuelle",
    "transmission": "Avant",
    "puissance": "70 kW (95 CH)",
    "type_de_vehicule": "Monospace",
    "sieges": 5,
    "portes": 5
  },
  {
    "lien_fiche": "https://www.autoscout24.fr/offres/volkswagen-amarok-amarok-dc-2-0-bitdi-trendline-4motion-ins-diesel-vert-56035b06-944b-447e-a88a-98cfb02498e8",
    "prix": "€ 11 900",
    "marque": "Volkswagen AmarokAmarok DC 2.0 bitdi Trendline 4motion ins.",
    "localisation": "36040 Sarego - Vicenza - VI",
    "kilometrage": 199000,
    "annee": 2011,
    "carburant": "Diesel",
    "boite_de_vitesse": "Manuelle",
    "transmission": "Arrière",
    "puissance": "120 kW (163 CH)",
    "type_de_vehicule": "SUV/4x4/Pick-Up",
    "sieges": 5,
    "portes": 4
  },
  {
    "lien_fiche": "https://www.autoscout24.fr/offres/mercedes-benz-a-180-cdi-avantgarde-diesel-noir-0fe4b1aa-b003-49b5-ad77-6a74089e51ab",
    "prix": "€ 2 450",
    "marque": "Mercedes-Benz A 180CDI Avantgarde",
    "localisation": "10126 Torino - TO",
    "kilometrage": 125000,
    "annee": 2006,
    "carburant": "Diesel",
    "boite_de_vitesse": "Manuelle",
    "transmission": "Avant",
    "puissance": "80 kW (109 CH)",
    "type_de_vehicule": "Berline",
    "sieges": 5,
    "portes": 5
  },
  {
    "lien_fiche": "https://www.autoscout24.fr/offres/bmw-x1-xdrive18d-business-auto-diesel-blanc-3880ff58-1b2a-4342-adbe-1d1fd953b42c",
    "prix": "€ 11 990",
    "marque": "BMW X1Xdrive18d Business auto",
    "localisation": "31012 Cappella Maggiore - Treviso - TV",
    "kilometrage": 178971,
    "annee": 2016,
    "carburant": "Diesel",
    "boite_de_vitesse": "Automatique",
    "transmission": "Arrière",
    "puissance": "110 kW (150 CH)",
    "type_de_vehicule": "SUV/4x4/Pick-Up",
    "sieges": 5,
    "portes": 5
  },
  {
    "lien_fiche": "https://www.autoscout24.fr/offres/citroen-c3-feel-1-5-diesel-102cv-diesel-rouge-338f7cd8-4234-4b95-bc19-508cebc9ea94",
    "prix": "€ 6 590",
    "marque": "Citroen C3Feel 1.5 Diesel 102CV",
    "localisation": "42122 Reggio Emilia RE",
    "kilometrage": 125469,
    "annee": null,
    "carburant": "Diesel",
    "boite_de_vitesse": "Manuelle",
    "transmission": "Avant",
    "puissance": "75 kW (102 CH)",
    "type_de_vehicule": "Citadine",
    "sieges": 5,
    "portes": 5
  },
  {
    "lien_fiche": "https://www.autoscout24.fr/offres/ford-focus-1-6-tdci-110cv-3p-tit-dpf-diesel-gris-efe0e068-5abc-476c-8a14-402114effb6f",
    "prix": "€ 1 950",
    "marque": "Ford Focus1.6 TDCi (110CV) 3p. Tit. DPF",
    "localisation": "10126 Torino - TO",
    "kilometrage": 149000,
    "annee": 2008,
    "carburant": "Diesel",
    "boite_de_vitesse": "Manuelle",
    "transmission": "Avant",
    "puissance": "80 kW (109 CH)",
    "type_de_vehicule": "Citadine",
    "sieges": 5,
    "portes": 3
  },
  {
    "lien_fiche": "https://www.autoscout24.fr/offres/citroen-c3-bluehdi-100-s-s-feel-diesel-blanc-c7ff747b-b747-42f4-8c0f-768d1af546f3",
    "prix": "€ 9 480",
    "marque": "Citroen C3BlueHDi 100 S&S Feel",
    "localisation": "00128 Roma",
    "kilometrage": 36908,
    "annee": null,
    "carburant": "Diesel",
    "boite_de_vitesse": "Manuelle",
    "transmission": "Avant",
    "puissance": "75 kW (102 CH)",
    "type_de_vehicule": "Berline",
    "sieges": 5,
    "portes": 5
  },
  {
    "lien_fiche": "https://www.autoscout24.fr/offres/mini-cooper-d-aut-brick-lane-panorama-dak-navi-bluetooth-diesel-noir-0828ea59-776d-42c1-9b7e-d5539124fbec",
    "prix": "€ 8 500",
    "marque": "MINI Cooper DAut. Brick Lane | Panorama Dak | Navi | Bluetooth",
    "localisation": "2382 Poppel",
    "kilometrage": 162676,
    "annee": 2014,
    "carburant": "Diesel",
    "boite_de_vitesse": "Automatique",
    "transmission": "Arrière",
    "puissance": "82 kW (111 CH)",
    "type_de_vehicule": "Berline",
    "sieges": 5,
    "portes": 5
  },
  {
    "lien_fiche": "https://www.autoscout24.fr/offres/emc-quattro-quattro-1-5-mt-essence-rouge-a6a55ead-46ce-40cb-90a8-866b8558fee7",
    "prix": "€ 14 990",
    "marque": "EMC QUATTROQuattro 1.5 MT",
    "localisation": "12062 Cherasco - Cuneo",
    "kilometrage": 1,
    "annee": 2025,
    "carburant": "Essence",
    "boite_de_vitesse": "Manuelle",
    "transmission": "Avant",
    "puissance": "76 kW (103 CH)",
    "type_de_vehicule": "SUV/4x4/Pick-Up",
    "sieges": 5,
    "portes": 5
  },
  {
    "lien_fiche": "https://www.autoscout24.fr/offres/mitsubishi-pajero-pinin-export-essence-bleu-866d11f7-c044-47f2-85cd-0a420c4301ab",
    "prix": "€ 1 399",
    "marque": "Mitsubishi Pajero Pinin*EXPORT*",
    "localisation": "12349 Berlin",
    "kilometrage": 196342,
    "annee": 2001,
    "carburant": "Essence",
    "boite_de_vitesse": "Automatique",
    "transmission": "4x4",
    "puissance": "88 kW (120 CH)",
    "type_de_vehicule": "SUV/4x4/Pick-Up",
    "sieges": 5,
    "portes": 2
  },
  {
    "lien_fiche": "https://www.autoscout24.fr/offres/skoda-kamiq-1-0-carplay-siege-chauffant-garantie-12-mois-essence-blanc-80365e24-e5b4-4a49-a8f3-dea6b2caabfc",
    "prix": "€ 16 990",
    "marque": "Skoda Kamiq1.0 - CARPLAY - SIEGE CHAUFFANT - GARANTIE 12 MOIS",
    "localisation": "1932 Zaventem",
    "kilometrage": 37645,
    "annee": 2022,
    "carburant": "Essence",
    "boite_de_vitesse": "Manuelle",
    "transmission": "Avant",
    "puissance": "81 kW (110 CH)",
    "type_de_vehicule": "SUV/4x4/Pick-Up",
    "sieges": 5,
    "portes": 5
  },
  {
    "lien_fiche": "https://www.autoscout24.fr/offres/mitsubishi-asx-1-6-117pk-intense-cleartec-technisch-goede-hoogzi-essence-gris-386425c4-a9ba-41ad-8641-85f7dcba4ebe",
    "prix": "€ 5 880",
    "marque": "Mitsubishi ASX1.6-117pk Intense ClearTec. Technisch goede hoogzi",
    "localisation": "8914 BG LEEUWARDEN",
    "kilometrage": 194809,
    "annee": 2011,
    "carburant": "Essence",
    "boite_de_vitesse": "Manuelle",
    "transmission": "Avant",
    "puissance": "86 kW (117 CH)",
    "type_de_vehicule": "SUV/4x4/Pick-Up",
    "sieges": 5,
    "portes": 5
  },
  {
    "lien_fiche": "https://www.autoscout24.fr/offres/volkswagen-golf-volkswagen-golf-1-6-tdi-dpf-dsg-5p-highline-unic-diesel-gris-940bff37-3cb8-4122-8bed-131730665406",
    "prix": "€ 4 300",
    "marque": "Volkswagen GolfVolkswagen Golf 1.6 TDI DPF DSG 5p. Highline Unic",
    "localisation": "10143 Torino - To",
    "kilometrage": 290000,
    "annee": null,
    "carburant": "Diesel",
    "boite_de_vitesse": "Manuelle",
    "transmission": "Avant",
    "puissance": "77 kW (105 CH)",
    "type_de_vehicule": "Berline",
    "sieges": 5,
    "portes": 5
  },
  {
    "lien_fiche": "https://www.autoscout24.fr/offres/alfa-romeo-giulia-2016-giulia-2-2-turbodiesel-160-cv-at8-b-tech-diesel-bleu-d1e3c4fd-521b-4e0c-b192-c9e0bd776005",
    "prix": "€ 19 900",
    "marque": "Alfa Romeo Giulia(2016) - Giulia 2.2 Turbodiesel 160 CV AT8 B-Tech",
    "localisation": "50142 Firenze - FI",
    "kilometrage": 97896,
    "annee": 2016,
    "carburant": "Diesel",
    "boite_de_vitesse": "Automatique",
    "transmission": "Avant",
    "puissance": "118 kW (160 CH)",
    "type_de_vehicule": "Berline",
    "sieges": 5,
    "portes": 4
  },
  {
    "lien_fiche": "https://www.autoscout24.fr/offres/opel-mokka-x-active-diesel-orange-5b8fb159-a117-4eeb-b451-12750941da23",
    "prix": "€ 10 500",
    "marque": "Opel Mokka XActive",
    "localisation": "30453 Hannover",
    "kilometrage": 120000,
    "annee": 2017,
    "carburant": "Diesel",
    "boite_de_vitesse": "Automatique",
    "transmission": "Avant",
    "puissance": "100 kW (136 CH)",
    "type_de_vehicule": "SUV/4x4/Pick-Up",
    "sieges": 5,
    "portes": 5
  },
  {
    "lien_fiche": "https://www.autoscout24.fr/offres/citroen-c4-1-2-e-thp-aut-feel-pack-nav-kam-virtu-led-18-essence-blanc-2b744215-03f1-4838-a7d0-d2b5f04fdef1",
    "prix": "€ 15 950",
    "marque": "Citroen C41.2 e-THP Aut Feel Pack NAV+KAM+VIRTU+LED+18",
    "localisation": "36179 Bebra",
    "kilometrage": 12658,
    "annee": null,
    "carburant": "Essence",
    "boite_de_vitesse": "Automatique",
    "transmission": "Avant",
    "puissance": "96 kW (131 CH)",
    "type_de_vehicule": "Berline",
    "sieges": 5,
    "portes": 4
  },
  {
    "lien_fiche": "https://www.autoscout24.fr/offres/alfa-romeo-159-1-9-jts-16v-s-wagon-progression-per-commercianti-essence-gris-4a703039-41f6-4542-82cf-1c4a8918088b",
    "prix": "€ 2 900",
    "marque": "Alfa Romeo 1591.9 JTS 16V S.wagon Progression PER COMMERCIANTI",
    "localisation": "21042 Caronno Pertusella - Varese - VA",
    "kilometrage": 165000,
    "annee": null,
    "carburant": "Essence",
    "boite_de_vitesse": "Manuelle",
    "transmission": "Avant",
    "puissance": "118 kW (160 CH)",
    "type_de_vehicule": "Break",
    "sieges": 5,
    "portes": 5
  },
  {
    "lien_fiche": "https://www.autoscout24.fr/offres/renault-megane-1-6-dynamique-5-drs-ecc-audio-cd-navigatie-lmv-17-essence-bleu-4c95c52a-972f-40ee-936b-1d8beddfb3e3",
    "prix": "€ 3 249",
    "marque": "Renault Megane1.6 Dynamique 5-Drs ECC Audio-CD/Navigatie LMV 17\"",
    "localisation": "1746 CM DIRKSHORN",
    "kilometrage": 205902,
    "annee": 2009,
    "carburant": "Essence",
    "boite_de_vitesse": "Manuelle",
    "transmission": "Avant",
    "puissance": "81 kW (110 CH)",
    "type_de_vehicule": "Citadine",
    "sieges": 5,
    "portes": 5
  },
  {
    "lien_fiche": "https://www.autoscout24.fr/offres/dacia-sandero-essentiel-inspektion-mit-kupplung-neu-essence-blanc-2769f37a-f230-441d-9997-df5e58adca0b",
    "prix": "€ 4 900",
    "marque": "Dacia SanderoEssentiel Inspektion mit Kupplung Neu",
    "localisation": "53757 Sankt Augustin",
    "kilometrage": 48000,
    "annee": 2017,
    "carburant": "Essence",
    "boite_de_vitesse": "Manuelle",
    "transmission": "Avant",
    "puissance": "54 kW (73 CH)",
    "type_de_vehicule": "Citadine",
    "sieges": 5,
    "portes": 5
  },
  {
    "lien_fiche": "https://www.autoscout24.fr/offres/ford-ecosport-1-0-ecoboost-titanium-schuifdak-half-leer-clima-essence-blanc-ee6ad359-b0bb-49c0-81cd-bd45b6c70835",
    "prix": "€ 7 649",
    "marque": "Ford EcoSport1.0 EcoBoost Titanium, Schuifdak, Half leer, Clima",
    "localisation": "6604 BS WIJCHEN",
    "kilometrage": 106724,
    "annee": 2015,
    "carburant": "Essence",
    "boite_de_vitesse": "Manuelle",
    "transmission": "Avant",
    "puissance": "93 kW (126 CH)",
    "type_de_vehicule": "SUV/4x4/Pick-Up",
    "sieges": 5,
    "portes": 5
  },
  {
    "lien_fiche": "https://www.autoscout24.fr/offres/audi-a3-sportback-1-4-tfsi-ambition-pro-line-s-essence-noir-d8da0ff4-3969-49cf-bb65-7a3dbff60a0e",
    "prix": "€ 4 450",
    "marque": "Audi A3Sportback 1.4 TFSI Ambition Pro Line S",
    "localisation": "3113 AH SCHIEDAM",
    "kilometrage": 262593,
    "annee": 2011,
    "carburant": "Essence",
    "boite_de_vitesse": "Manuelle",
    "transmission": "Avant",
    "puissance": "92 kW (125 CH)",
    "type_de_vehicule": "Citadine",
    "sieges": 5,
    "portes": 5
  },
  {
    "lien_fiche": "https://www.autoscout24.fr/offres/hyundai-i30-i30-sw-1-4i-ess-essence-noir-aa4366ac-a1b6-4b5d-a7ca-5476faa8b2ff",
    "prix": "€ 3 990",
    "marque": "Hyundai i30i30 SW 1.4i*ESS*",
    "localisation": "6180 Courcelles",
    "kilometrage": 143816,
    "annee": 2010,
    "carburant": "Essence",
    "boite_de_vitesse": "Manuelle",
    "transmission": "Avant",
    "puissance": "80 kW (109 CH)",
    "type_de_vehicule": "Break",
    "sieges": 5,
    "portes": 5
  },
  {
    "lien_fiche": "https://www.autoscout24.fr/offres/volkswagen-fox-diesel-argent-39fdd38c-4252-4de8-9106-e10ff10378e5",
    "prix": "€ 800",
    "marque": "Volkswagen Fox",
    "localisation": "38444 Wolfsburg Heiligendorf",
    "kilometrage": 316755,
    "annee": 2006,
    "carburant": "Diesel",
    "boite_de_vitesse": "Manuelle",
    "transmission": "Boîte manuelle",
    "puissance": "51 kW (69 CH)",
    "type_de_vehicule": "Citadine",
    "sieges": null,
    "portes": 3
  },
  {
    "lien_fiche": "https://www.autoscout24.fr/offres/citroen-c3-100-max-fin-9perfet-sc34-essence-gris-0798baa4-39cb-493c-8949-436aa43498eb",
    "prix": "€ 14 500",
    "marque": "Citroen C3100 Max Fin 9Perfet Sc34%",
    "localisation": "10041 Carignano - To",
    "kilometrage": 19981,
    "annee": null,
    "carburant": "Essence",
    "boite_de_vitesse": "Manuelle",
    "transmission": "Avant",
    "puissance": "74 kW (101 CH)",
    "type_de_vehicule": "Berline",
    "sieges": 5,
    "portes": 5
  },
  {
    "lien_fiche": "https://www.autoscout24.fr/offres/audi-a3-audi-a3-sportback-30-tdi-design-navi-led-shz-dab-diesel-argent-d0e8f51c-0ec4-4e1f-90dd-03c40fbd7a82",
    "prix": "€ 12 500",
    "marque": "Audi A3Audi A3 Sportback 30 TDI design Navi+LED+SHZ+DAB",
    "localisation": "65428 Rüsselsheim",
    "kilometrage": 141000,
    "annee": 2019,
    "carburant": "Diesel",
    "boite_de_vitesse": "Manuelle",
    "transmission": "Avant",
    "puissance": "85 kW (116 CH)",
    "type_de_vehicule": "Berline",
    "sieges": 5,
    "portes": 5
  },
  {
    "lien_fiche": "https://www.autoscout24.fr/offres/dr-automobiles-dr6-1-5-turbo-bi-fuel-gpl-gris-3c0e4b24-541b-45f6-8d7f-3e246ba2deb5",
    "prix": "€ 16 450",
    "marque": "DR Automobiles DR61.5 Turbo Bi-Fuel",
    "localisation": "20025 Legnano - MI - Milano",
    "kilometrage": 36307,
    "annee": null,
    "carburant": "Électrique",
    "boite_de_vitesse": "Automatique",
    "transmission": "Avant",
    "puissance": "110 kW (150 CH)",
    "type_de_vehicule": "SUV/4x4/Pick-Up",
    "sieges": 5,
    "portes": 5
  },
  {
    "lien_fiche": "https://www.autoscout24.fr/offres/lexus-ux-200-ux-2020-250h-2-0-luxury-2wd-cvt-electrique-essence-argent-39cddf36-988e-44e8-b283-2a44a04b6bf8",
    "prix": "€ 22 990",
    "marque": "Lexus UX 200UX 2020 250h 2.0 Luxury 2wd cvt",
    "localisation": "20077 Melegnano - Milano - MI",
    "kilometrage": 24000,
    "annee": 2020,
    "carburant": "Essence",
    "boite_de_vitesse": "Automatique",
    "transmission": "Avant",
    "puissance": "112 kW (152 CH)",
    "type_de_vehicule": "SUV/4x4/Pick-Up",
    "sieges": 5,
    "portes": 5
  },
  {
    "lien_fiche": "https://www.autoscout24.fr/offres/opel-astra-j-sports-edition-motor-macht-geraeusch-diesel-argent-b52de14b-644e-4082-afdd-2142486fd864",
    "prix": "€ 2 200",
    "marque": "Opel AstraJ Sports Edition Motor macht Geräusch",
    "localisation": "99947 Bad Langensalza",
    "kilometrage": 293414,
    "annee": 2011,
    "carburant": "Diesel",
    "boite_de_vitesse": "Manuelle",
    "transmission": "Boîte manuelle",
    "puissance": "118 kW (160 CH)",
    "type_de_vehicule": "Break",
    "sieges": 5,
    "portes": 4
  },
  {
    "lien_fiche": "https://www.autoscout24.fr/offres/bmw-318-d-2-0-143cv-cat-touring-attiva-diesel-gris-414304bf-3862-4893-b533-4c19c0cc56ab",
    "prix": "€ 4 800",
    "marque": "BMW 318d 2.0 143CV cat Touring Attiva",
    "localisation": "21042 Caronno Pertusella - Varese - VA",
    "kilometrage": 265600,
    "annee": 2012,
    "carburant": "Diesel",
    "boite_de_vitesse": "Automatique",
    "transmission": "Avant",
    "puissance": "105 kW (143 CH)",
    "type_de_vehicule": "Break",
    "sieges": 5,
    "portes": 5
  },
  {
    "lien_fiche": "https://www.autoscout24.fr/offres/volkswagen-polo-5p-1-4-59000-km-essence-gris-4d9b5f29-f264-491d-87e4-d62a8c0eb549",
    "prix": "€ 7 300",
    "marque": "Volkswagen Polo5p 1.4 / 59000 KM",
    "localisation": "24040 Lallio - Bergamo - BG",
    "kilometrage": 59000,
    "annee": null,
    "carburant": "Essence",
    "boite_de_vitesse": "Manuelle",
    "transmission": "Arrière",
    "puissance": "63 kW (86 CH)",
    "type_de_vehicule": "Berline",
    "sieges": 5,
    "portes": 5
  }
]